graphrag_eval/__init__.py
graphrag_eval/aggregation.py
graphrag_eval/answer_correctness.py
graphrag_eval/answer_relevance.py
graphrag_eval/evaluation.py
graphrag_eval/prompts/template.md
graphrag_eval/steps/__init__.py
graphrag_eval/steps/evaluation.py
graphrag_eval/steps/retrieval_answer.py
graphrag_eval/steps/retrieval_context_ids.py
graphrag_eval/steps/retrieval_context_texts.py
graphrag_eval/steps/sparql.py
graphrag_eval/util.py
graphrag_eval-5.2.0.dist-info/LICENSE
graphrag_eval-5.2.0.dist-info/METADATA
graphrag_eval-5.2.0.dist-info/WHEEL
graphrag_eval-5.2.0.dist-info/entry_points.txt
graphrag_eval-5.2.0.dist-info/RECORD
