Metadata-Version: 2.3
Name: graphrag-eval
Version: 5.2.0
Summary: For assessing question answering systems' final answers and intermediate steps, against a given set of questions, reference answers and steps.
License: Apache-2.0
Author: Philip Ganchev
Author-email: philip.ganchev@graphwise.ai
Requires-Python: >=3.12,<3.13
Classifier: License :: OSI Approved :: Apache Software License
Classifier: Programming Language :: Python :: 3
Classifier: Programming Language :: Python :: 3.12
Provides-Extra: ragas
Requires-Dist: langchain-openai (==0.3.7) ; extra == "ragas"
Requires-Dist: langchain_community (==0.3.18) ; extra == "ragas"
Requires-Dist: langevals[ragas] (==0.1.8) ; extra == "ragas"
Requires-Dist: litellm (==1.61.20) ; extra == "ragas"
Requires-Dist: ragas (==0.2.9) ; extra == "ragas"
Project-URL: Repository, https://github.com/Ontotext-AD/graphrag-eval
